yellowdot/__init__.py
yellowdot/firebase/YDFBUserUtils.py
yellowdot/firebase/YDFirebase.py
yellowdot/firebase/YDFirebaseFCM.py
yellowdot/firebase/__init__.py
yellowdot/models/FBUserResponse.py
yellowdot/models/Response.py
yellowdot/models/__init__.py
yellowdot/rbac/RBAC.py
yellowdot/rbac/__init__.py
yellowdot/utils/FileLogger.py
yellowdot/utils/TimeUtils.py
yellowdot/utils/YDCommon.py
yellowdot/utils/YDLogger.py
yellowdot/utils/__init__.py
yd_base-1.0.3.dist-info/METADATA
yd_base-1.0.3.dist-info/WHEEL
yd_base-1.0.3.dist-info/top_level.txt
yd_base-1.0.3.dist-info/RECORD
