Metadata-Version: 2.1
Name: yd-base
Version: 1.0.3
Summary: A python package for yellowdot's base classes and Utilities
Home-page: https://github.com/Yellow-Dot-Energy-Company-Ltd/yd_base_py
Author: Bruno Kiprop and Jamie Omondi
Author-email: brunookiprop@gmail.com,cruiseomondi90@gmail.com
License: MIT,GNU
Platform: UNKNOWN
Requires-Dist: firebase-admin
